llama_index/embeddings/siliconflow/__init__.py
llama_index/embeddings/siliconflow/base.py
llama_index_embeddings_siliconflow-0.3.1.dist-info/METADATA
llama_index_embeddings_siliconflow-0.3.1.dist-info/WHEEL
llama_index_embeddings_siliconflow-0.3.1.dist-info/licenses/LICENSE
llama_index_embeddings_siliconflow-0.3.1.dist-info/RECORD
