Metadata-Version: 2.4
Name: llama-index-embeddings-siliconflow
Version: 0.3.1
Summary: llama-index embeddings siliconflow integration
Author-email: nightosong <nightosong2013@gmail.com>
License-Expression: MIT
License-File: LICENSE
Requires-Python: <4.0,>=3.9
Requires-Dist: aiohttp
Requires-Dist: llama-index-core<0.15,>=0.13.0
